winzy_extract/__init__.py
winzy_extract-0.1.dist-info/LICENSE
winzy_extract-0.1.dist-info/METADATA
winzy_extract-0.1.dist-info/WHEEL
winzy_extract-0.1.dist-info/entry_points.txt
winzy_extract-0.1.dist-info/top_level.txt
winzy_extract-0.1.dist-info/RECORD
