Metadata-Version: 2.1
Name: winzy-extract
Version: 0.1
Summary: Extracts text from a file based on input and output line numbers
Author: Sukhbinder Singh
License: Apache-2.0
Project-URL: Homepage, https://github.com/sukhbinder/winzy-extract
Project-URL: Changelog, https://github.com/sukhbinder/winzy-extract/releases
Project-URL: Issues, https://github.com/sukhbinder/winzy-extract/issues
Project-URL: CI, https://github.com/sukhbinder/winzy-extract/actions
Classifier: License :: OSI Approved :: Apache Software License
License-File: LICENSE
Requires-Dist: winzy
Provides-Extra: test
Requires-Dist: pytest ; extra == 'test'
